{
  "0": {
    "wdl": "tests/standard_library/basic_stdout.wdl",
    "json": "tests/standard_library/basic_stdout.json",
    "outputs": [
       {
         "type": "File",
         "identifier": "stdoutWorkflow.get_stdout.check_this",
         "md5sum": "91d69f7c47b6e7d5e4d81fab67f7f304",
         "size": "19"
       }
    ],
    "description": "Standard Lib: basic stdout() test in draft-2",
    "versions_supported": ["draft-2"]
  },
  "1": {
    "wdl": "tests/standard_library/basic_stderr.wdl",
    "json": "tests/standard_library/basic_stderr.json",
    "outputs": [
       {
         "type": "File",
         "identifier": "stderrWorkflow.get_stderr.check_this",
         "md5sum": "2332021c3feef276abe077f34276abfe",
         "size": "29"
       }
    ],
    "description": "Standard Lib: basic stderr() test in draft-2",
    "versions_supported": ["draft-2"]
  },
  "2": {
    "wdl": "tests/standard_library/basic_ceil.wdl",
    "json": "tests/standard_library/basic_ceil.json",
    "outputs": [
       {
         "type": "Int",
         "identifier": "ceilWorkflow.get_ceil.the_ceiling",
         "value": 12
       }
    ],
    "description": "Standard Lib: basic ceil() test in draft-2",
    "versions_supported": ["draft-2"]
  },
  "3": {
    "wdl": "tests/standard_library/basic_stdout_1.0.wdl",
    "json": "tests/standard_library/basic_stdout.json",
    "outputs": [
       {
         "type": "File",
         "identifier": "stdoutWorkflow.check_this",
         "md5sum": "91d69f7c47b6e7d5e4d81fab67f7f304",
         "size": "19"
       }
    ],
    "description": "Standard Lib: basic stdout() test",
    "versions_supported": ["1.0"]
  },
  "4": {
    "wdl": "tests/standard_library/basic_stderr_1.0.wdl",
    "json": "tests/standard_library/basic_stderr.json",
    "outputs": [
       {
         "type": "File",
         "identifier": "stderrWorkflow.check_this",
         "md5sum": "2332021c3feef276abe077f34276abfe",
         "size": "29"
       }
    ],
    "description": "Standard Lib: basic stderr() test",
    "versions_supported": ["1.0"]
  },
  "5": {
    "wdl": "tests/standard_library/basic_ceil_1.0.wdl",
    "json": "tests/standard_library/basic_ceil.json",
    "outputs": [
       {
         "type": "Int",
         "identifier": "ceilWorkflow.the_ceiling",
         "value": 12
       }
    ],
    "description": "Standard Lib: basic ceil() test",
    "versions_supported": ["1.0"]
  },
  "6": {
    "wdl": "tests/parser/string_placeholders_1.1.wdl",
    "json": "tests/parser/empty.json",
    "outputs": [
       {
         "type": "Array[String]",
         "identifier": "placeholderWorkflow.ones",
         "value": ["1", "1", "1", "1", "1", "1", "1", "1", "1", "1", "1", "1", "1"]
       }
    ],
    "description": "Parser: expression placeholders in strings in 1.1",
    "versions_supported": ["1.1"]
  },
  "7": {
    "wdl": "tests/parser/string_placeholders_in_conditionals_1.1.wdl",
    "json": "tests/parser/empty.json",
    "outputs": [
       {
         "type": "String",
         "identifier": "placeholderWorkflow.result",
         "value": "yep"
       }
    ],
    "description": "Parser: expression placeholders in strings in conditional expressions in 1.1",
    "versions_supported": ["1.1"]
  },
  "8": {
    "wdl": "tests/parser/string_placeholders_in_conditionals_1.0.wdl",
    "json": "tests/parser/empty.json",
    "outputs": [
       {
         "type": "String",
         "identifier": "placeholderWorkflow.result",
         "value": "[\"cromwell\"]"
       }
    ],
    "description": "Parser: expression placeholders in strings in conditional expressions in 1.0, Cromwell style",
    "versions_supported": ["1.0-cromwell-bugs"]
  },
  "9": {
    "wdl": "tests/semantics/null_optional_vs_default_1.0.wdl",
    "json": "tests/semantics/empty.json",
    "outputs": [
       {
         "type": "Int",
         "identifier": "overrideWorkflow.result",
         "value": 1
       }
    ],
    "description": "Semantics: passing a null optional value as an input to a task does not override a default value with null",
    "versions_supported": ["1.0"]
  },
  "10": {
    "wdl": "tests/semantics/null_input_through_workflows_1.0.wdl",
    "json": "tests/semantics/empty.json",
    "outputs": [
       {
         "type": "Int",
         "identifier": "nullInput.result",
         "value": 1
       }
    ],
    "description": "Semantics: passing a null optional value as an input to a workflow that calls subworkflows does not override a default value with null",
    "versions_supported": ["1.0"]
  },
  "11": {
    "wdl": "tests/semantics/null_input_through_workflows_1.0.wdl",
    "json": "tests/semantics/nonnull_input.json",
    "outputs": [
       {
         "type": "Int",
         "identifier": "nullInput.result",
         "value": 10
       }
    ],
    "description": "Semantics: passing a non-null optional value as an input to a workflow that calls subworkflows brings it through",
    "versions_supported": ["1.0"]
  },
  "12": {
    "wdl": "tests/standard_library/basic_sep.wdl",
    "json": "tests/standard_library/basic_sep.json",
    "outputs": [
       {
         "type": "String",
         "identifier": "sepWorkflow.str_result",
         "value": "a - b - c"
       }
    ],
    "description": "Standard Lib: basic sep() test in 1.1",
    "versions_supported": ["1.1"]
  },
  "13": {
    "wdl": "tests/standard_library/basic_prefix.wdl",
    "json": "tests/standard_library/basic_prefix.json",
    "outputs": [
       {
         "type": "Array[String]",
         "identifier": "prefixWorkflow.result",
         "value": ["-e value1", "-e value2", "-e value3"]
       }
    ],
    "description": "Standard Lib: basic prefix() test with strings in draft-2",
    "versions_supported": ["draft-2"]
  },
  "14": {
    "wdl": "tests/standard_library/basic_prefix_1.0.wdl",
    "json": "tests/standard_library/basic_prefix.json",
    "outputs": [
       {
         "type": "Array[String]",
         "identifier": "prefixWorkflow.result",
         "value": ["-e value1", "-e value2", "-e value3"]
       }
    ],
    "description": "Standard Lib: basic prefix() test with strings in 1.0",
    "versions_supported": ["1.0"]
  },
  "15": {
    "wdl": "tests/standard_library/basic_quote.wdl",
    "json": "tests/standard_library/basic_quote.json",
    "outputs": [
       {
         "type": "Array[String]",
         "identifier": "quoteWorkflow.result",
         "value": [["\"value1\"", "\"value2\"", "\"value3\""], ["\"1\"", "\"2\"", "\"-3\""], ["\"1.234000\"", "\"-0.543000\"", "\"13.300000\""], ["\"True\"", "\"False\"", "\"True\""]]
       }
    ],
    "description": "Standard Lib: basic quote() test with strings in 1.1",
    "versions_supported": ["1.1"]
  },
  "16": {
    "wdl": "tests/standard_library/basic_squote.wdl",
    "json": "tests/standard_library/basic_squote.json",
    "outputs": [
       {
         "type": "Array[String]",
         "identifier": "squoteWorkflow.result",
         "value": ["'value1'", "'value2'", "'value3'"]
       }
    ],
    "description": "Standard Lib: basic squote() test with strings in 1.1",
    "versions_supported": ["1.1"]
  },
  "17": {
    "wdl": "tests/standard_library/basic_select_first.wdl",
    "json": "tests/standard_library/basic_select_first.json",
    "outputs": [
       {
         "type": "Int",
         "identifier": "selectFirstWorkflow.result",
         "value": 5
       }
    ],
    "description": "Standard Lib: basic select_first() test in draft-2",
    "versions_supported": ["draft-2"]
  },
  "18": {
    "wdl": "tests/standard_library/basic_select_first_1.0.wdl",
    "json": "tests/standard_library/basic_select_first.json",
    "outputs": [
       {
         "type": "Int",
         "identifier": "selectFirstWorkflow.result",
         "value": 5
       }
    ],
    "description": "Standard Lib: basic select_first() test in 1.0",
    "versions_supported": ["1.0"]
  },
  "19": {
    "wdl": "tests/standard_library/basic_basename.wdl",
    "json": "tests/standard_library/basic_basename.json",
    "outputs": [
       {
         "type": "String",
         "identifier": "basenameWorkflow.result",
         "value": "file.txt"
       }
    ],
    "description": "Standard Lib: basic basename() test in draft-2",
    "versions_supported": ["draft-2"]
  },
  "20": {
    "wdl": "tests/standard_library/basic_basename_1.0.wdl",
    "json": "tests/standard_library/basic_basename.json",
    "outputs": [
       {
         "type": "String",
         "identifier": "basenameWorkflow.result",
         "value": "file.txt"
       }
    ],
    "description": "Standard Lib: basic basename() test in 1.0",
    "versions_supported": ["1.0"]
  },
  "21": {
    "wdl": "tests/standard_library/basic_basename_opt.wdl",
    "json": "tests/standard_library/basic_basename_opt.json",
    "outputs": [
       {
         "type": "String",
         "identifier": "basenameWorkflowOpt.result",
         "value": "file"
       }
    ],
    "description": "Standard Lib: basic basename() test with optional arguments in draft-2",
    "versions_supported": ["draft-2"]
  },
  "22": {
    "wdl": "tests/standard_library/basic_basename_opt_1.0.wdl",
    "json": "tests/standard_library/basic_basename_opt.json",
    "outputs": [
       {
         "type": "String",
         "identifier": "basenameWorkflowOpt.result",
         "value": "file"
       }
    ],
    "description": "Standard Lib: basic basename() test with optional arguments in 1.0",
    "versions_supported": ["1.0"]
  },
  "23": {
    "wdl": "tests/standard_library/basic_defined.wdl",
    "json": "tests/standard_library/basic_defined.json",
    "outputs": [
       {
         "type": "Boolean",
         "identifier": "definedWorkflow.result",
         "value": true
       }
    ],
    "description": "Standard Lib: basic defined() test in draft-2",
    "versions_supported": ["draft-2"]
  },
  "24": {
    "wdl": "tests/standard_library/basic_defined_1.0.wdl",
    "json": "tests/standard_library/basic_defined.json",
    "outputs": [
       {
         "type": "Boolean",
         "identifier": "definedWorkflow.result",
         "value": true
       }
    ],
    "description": "Standard Lib: basic defined() test in 1.0",
    "versions_supported": ["1.0"]
  },
  "25": {
    "wdl": "tests/standard_library/basic_defined.wdl",
    "json": "tests/standard_library/empty.json",
    "outputs": [
       {
         "type": "Boolean",
         "identifier": "definedWorkflow.result",
         "value": false
       }
    ],
    "description": "Standard Lib: basic defined() test with empty input in draft-2",
    "versions_supported": ["draft-2"]
  },
  "26": {
    "wdl": "tests/standard_library/basic_defined_1.0.wdl",
    "json": "tests/standard_library/empty.json",
    "outputs": [
       {
         "type": "Boolean",
         "identifier": "definedWorkflow.result",
         "value": false
       }
    ],
    "description": "Standard Lib: basic defined() test with empty input in 1.0",
    "versions_supported": ["1.0"]
  },
  "27": {
    "wdl": "tests/standard_library/basic_select_all.wdl",
    "json": "tests/standard_library/basic_select_all.json",
    "outputs": [
       {
         "type": "Array[Int]",
         "identifier": "selectAllWorkflow.result",
         "value": [4, 5, 7]
       }
    ],
    "description": "Standard Lib: basic select_all() test in draft-2",
    "versions_supported": ["draft-2"]
  },
  "28": {
    "wdl": "tests/standard_library/basic_select_all_1.0.wdl",
    "json": "tests/standard_library/basic_select_all.json",
    "outputs": [
       {
         "type": "Array[Int]",
         "identifier": "selectAllWorkflow.result",
         "value": [4, 5, 7]
       }
    ],
    "description": "Standard Lib: basic select_all() test in 1.0",
    "versions_supported": ["1.0"]
  },
  "29": {
    "wdl": "tests/standard_library/basic_suffix.wdl",
    "json": "tests/standard_library/basic_suffix.json",
    "outputs": [
       {
         "type": "Array[String]",
         "identifier": "suffixWorkflow.result",
         "value": ["value1.txt", "value2.txt", "value3.txt"]
       }
    ],
    "description": "Standard Lib: basic suffix() test in 1.1",
    "versions_supported": ["1.1"]
  }
}
